Workbook
Name Aporte: APP!$D$10
Name Quantidade_Anos: APP!$D$11
Name Rendimento_Carteira: APP!$C$6
Name salario: APP!$C$5
Name sugestao_investimento: APP!$B$7
Name Taxa_Mensal: APP!$D$12

Sheet APP
B3: CONFIGURAÇÕES
B5: Salário | C5: 2000
B6: Rendimento Carteira | C6: 0.006
B7: Sugestão de Investimento (30%) | C7: =salario*30% -> 600
B9: INVESTIMENTO MENSAL
A10: 2 | B10: Quantos investir por mês? | D10: 200
A11: 5 | B11: Por Quantos Anos? | D11: 5
A12: 10 | B12: Taxa de Rendimento Mensal? | D12: 0.01079
A13: 20 | B13: Patrimônio Acumulado? | D13: =FV(Taxa_Mensal,Quantidade_Anos*12,Aporte*-1,) -> 16755.383
A14: 30 | B14: Dividendos Mensais? | D14: =D13*$C$6 -> 100.5323
B16: CENÁRIOS | D16: DIVIDENDO
B17: Quanto em 2 anos? | C17: =FV($D$12,$A10*12,$D$10*-1) -> 5445.5255 | D17: =C17*Rendimento_Carteira -> 32.673153
B18: Quanto em 5 anos? | C18: =FV($D$12,$A11*12,$D$10*-1) -> 16755.383 | D18: =C18*Rendimento_Carteira -> 100.5323
B19: Quanto em 10 anos? | C19: =FV($D$12,$A12*12,$D$10*-1) -> 48656.843 | D19: =C19*Rendimento_Carteira -> 291.94106
B20: Quanto em 20 anos? | C20: =FV($D$12,$A13*12,$D$10*-1) -> 225039.68 | D20: =C20*Rendimento_Carteira -> 1350.2381
B21: Quanto em 30 anos? | C21: =FV($D$12,$A14*12,$D$10*-1) -> 864433.93 | D21: =C21*Rendimento_Carteira -> 5186.6036
B23: Perfil | C23: AGRESSIVO
B24: VALOR A SER INVESTIDO POR MÊS | C24: 200
B26: TIPO DE FII | C26: PERCENTUAL SUGERIDO | D26: VALORES
B27: PAPEL | C27: =VLOOKUP($C$23&"-"&B27,'TABELA DE APOIO'!$A:$D,4,FALSE) -> 0.5 | D27: =C27*$C$24 -> 100
B28: TIJOLO | C28: =VLOOKUP($C$23&"-"&B28,'TABELA DE APOIO'!$A:$D,4,FALSE) -> 0.1 | D28: =C28*$C$24 -> 20
B29: HÍBRIDOS | C29: =VLOOKUP($C$23&"-"&B29,'TABELA DE APOIO'!$A:$D,4,FALSE) -> 0.05 | D29: =C29*$C$24 -> 10
B30: FOFs | C30: =VLOOKUP($C$23&"-"&B30,'TABELA DE APOIO'!$A:$D,4,FALSE) -> 0.05 | D30: =C30*$C$24 -> 10
B31: DESENVOLVIMENTO | C31: =VLOOKUP($C$23&"-"&B31,'TABELA DE APOIO'!$A:$D,4,FALSE) -> 0.2 | D31: =C31*$C$24 -> 40
B32: HOTELARIAS | C32: =VLOOKUP($C$23&"-"&B32,'TABELA DE APOIO'!$A:$D,4,FALSE) -> 0.1 | D32: =C32*$C$24 -> 20
B33: TOTAL | D33: =SUM(D27:D32) -> 200

Sheet TABELA DE APOIO
A1: CHAVE | B1: PERFIL | C1: TIPO DE FII | D1: PERCENTUAL
A2: =$B$2&"-"&C2 -> CONSERVADOR-PAPEL | B2: CONSERVADOR | C2: PAPEL | D2: 0.3
A3: =$B$2&"-"&C3 -> CONSERVADOR-TIJOLO | B3: CONSERVADOR | C3: TIJOLO | D3: 0.5
A4: =$B$2&"-"&C4 -> CONSERVADOR-HÍBRIDOS | B4: CONSERVADOR | C4: HÍBRIDOS | D4: 0.1
A5: =$B$2&"-"&C5 -> CONSERVADOR-FOFs | B5: CONSERVADOR | C5: FOFs | D5: 0.1
A6: =$B$2&"-"&C6 -> CONSERVADOR-DESENVOLVIMENTO | B6: CONSERVADOR | C6: DESENVOLVIMENTO | D6: 0
A7: =$B$2&"-"&C7 -> CONSERVADOR-HOTELARIAS | B7: CONSERVADOR | C7: HOTELARIAS | D7: 0
A8: =$B$8&"-"&C8 -> MODERADO-PAPEL | B8: MODERADO | C8: PAPEL | D8: 0.32
A9: =$B$8&"-"&C9 -> MODERADO-TIJOLO | B9: MODERADO | C9: TIJOLO | D9: 0.4
A10: =$B$8&"-"&C10 -> MODERADO-HÍBRIDOS | B10: MODERADO | C10: HÍBRIDOS | D10: 0.08
A11: =$B$8&"-"&C11 -> MODERADO-FOFs | B11: MODERADO | C11: FOFs | D11: 0.1
A12: =$B$8&"-"&C12 -> MODERADO-DESENVOLVIMENTO | B12: MODERADO | C12: DESENVOLVIMENTO | D12: 0.1
A13: =$B$8&"-"&C13 -> MODERADO-HOTELARIAS | B13: MODERADO | C13: HOTELARIAS | D13: 0
A14: =$B$14&"-"&C14 -> AGRESSIVO-PAPEL | B14: AGRESSIVO | C14: PAPEL | D14: 0.5
A15: =$B$14&"-"&C15 -> AGRESSIVO-TIJOLO | B15: AGRESSIVO | C15: TIJOLO | D15: 0.1
A16: =$B$14&"-"&C16 -> AGRESSIVO-HÍBRIDOS | B16: AGRESSIVO | C16: HÍBRIDOS | D16: 0.05
A17: =$B$14&"-"&C17 -> AGRESSIVO-FOFs | B17: AGRESSIVO | C17: FOFs | D17: 0.05
A18: =$B$14&"-"&C18 -> AGRESSIVO-DESENVOLVIMENTO | B18: AGRESSIVO | C18: DESENVOLVIMENTO | D18: 0.2
A19: =$B$14&"-"&C19 -> AGRESSIVO-HOTELARIAS | B19: AGRESSIVO | C19: HOTELARIAS | D19: 0.1
